vpype_rerun/__init__.py
vpype_rerun/rerun.py
vpype_rerun-0.1.0.dist-info/LICENSE
vpype_rerun-0.1.0.dist-info/METADATA
vpype_rerun-0.1.0.dist-info/WHEEL
vpype_rerun-0.1.0.dist-info/entry_points.txt
vpype_rerun-0.1.0.dist-info/RECORD
