Metadata-Version: 2.1
Name: vpype-rerun
Version: 0.1.0
Summary: Rerun viewer integration for vpype
License: MIT
Author: Antoine Beyeler
Author-email: abeyeler@ab-ware.com
Requires-Python: >=3.9,<3.12
Classifier: Development Status :: 4 - Beta
Classifier: Environment :: Plugins
Classifier: License :: OSI Approved :: MIT License
Classifier: Programming Language :: Python :: 3
Classifier: Programming Language :: Python :: 3.9
Classifier: Programming Language :: Python :: 3.10
Classifier: Programming Language :: Python :: 3.11
Classifier: Topic :: Multimedia :: Graphics
Requires-Dist: click (>=8.1.6)
Requires-Dist: rerun-sdk (>=0.8.0)
Requires-Dist: vpype[all] (>=1.13)
